python312/Lib/site-packages/LiBrH2O.py
LiBrH2O-0.1.2.dist-info/METADATA
LiBrH2O-0.1.2.dist-info/WHEEL
LiBrH2O-0.1.2.dist-info/top_level.txt
LiBrH2O-0.1.2.dist-info/RECORD
