Metadata-Version: 2.1
Name: LiBrH2O
Version: 0.1.2
Summary: A python library of LiBrH2O properties
Home-page: https://github.com/syq-tju
Author: Rishi_Shi
Author-email: syq.zju@gmail.com
License: UNKNOWN
Platform: UNKNOWN
